fileops/__init__.py
fileops/jsonops.py
fileops/textfiles.py
simple_file_ops-0.1.3.dist-info/LICENSE
simple_file_ops-0.1.3.dist-info/METADATA
simple_file_ops-0.1.3.dist-info/WHEEL
simple_file_ops-0.1.3.dist-info/top_level.txt
simple_file_ops-0.1.3.dist-info/RECORD
