Metadata-Version: 2.1
Name: simple-file-ops
Version: 0.1.3
Summary: Do simple operations for files easier
Home-page: UNKNOWN
Author: Cube Riser
Author-email: cuberiser@gmail.com
License: MIT
Keywords: python,file operations,files,fileops,file-operations,simple file ops,file ops
Platform: UNKNOWN
Classifier: Development Status :: 1 - Planning
Classifier: Intended Audience :: Developers
Classifier: Programming Language :: Python :: 3
Classifier: Operating System :: Unix
Classifier: Operating System :: MacOS :: MacOS X
Classifier: Operating System :: Microsoft :: Windows
License-File: LICENSE
